pypwsafev3/PWSafeV3Headers.py
pypwsafev3/PWSafeV3Records.py
pypwsafev3/__init__.py
pypwsafev3/consts.py
pypwsafev3/errors.py
pypwsafev3-0.0.3.dist-info/METADATA
pypwsafev3-0.0.3.dist-info/RECORD
pypwsafev3-0.0.3.dist-info/WHEEL
pypwsafev3-0.0.3.dist-info/top_level.txt
