Metadata-Version: 2.1
Name: pypwsafev3
Version: 0.0.3
Summary: A pure-Python library (based on https://github.com/ronys/pypwsafe and it's forks) that can read and write Password Safe v3 files, originally by Paulson McIntyre http://pwsafe.org
Home-page: https://github.com/voytecPL/pypwsafev3
Author: Wojciech Jakubas
Author-email: wojciech.jakubas@gmail.com
License: UNKNOWN
Platform: UNKNOWN
Classifier: Programming Language :: Python :: 3
Classifier: License :: OSI Approved :: GNU General Public License (GPL)
Classifier: Operating System :: OS Independent
Requires-Dist: pycryptoplus
Requires-Dist: pycryptodome
